devicetree/__init__.py
devicetree/_private.py
devicetree/dtlib.py
devicetree/edtlib.py
devicetree/edtlib_legacy_fix.py
devicetree/grutils.py
devicetree/py.typed
devicetree/typed.py
dtsh/__init__.py
dtsh/autocomp.py
dtsh/cli.py
dtsh/config.py
dtsh/dts.py
dtsh/dtsh.ini
dtsh/errors.py
dtsh/hwm.py
dtsh/io.py
dtsh/model.py
dtsh/modelutils.py
dtsh/rl.py
dtsh/session.py
dtsh/shell.py
dtsh/shellutils.py
dtsh/typed.py
dtsh/utils.py
dtsh/builtins/__init__.py
dtsh/builtins/alias.py
dtsh/builtins/cat.py
dtsh/builtins/cd.py
dtsh/builtins/chosen.py
dtsh/builtins/echo.py
dtsh/builtins/find.py
dtsh/builtins/ls.py
dtsh/builtins/pwd.py
dtsh/builtins/tree.py
dtsh/builtins/uname.py
dtsh/rich/__init__.py
dtsh/rich/autocomp.py
dtsh/rich/html.py
dtsh/rich/io.py
dtsh/rich/modelview.py
dtsh/rich/session.py
dtsh/rich/shellutils.py
dtsh/rich/svg.py
dtsh/rich/text.py
dtsh/rich/theme.ini
dtsh/rich/theme.py
dtsh/rich/tui.py
dtsh-0.2.4.dist-info/LICENSE
dtsh-0.2.4.dist-info/METADATA
dtsh-0.2.4.dist-info/WHEEL
dtsh-0.2.4.dist-info/entry_points.txt
dtsh-0.2.4.dist-info/top_level.txt
dtsh-0.2.4.dist-info/RECORD
