Metadata-Version: 2.1
Name: dtsh
Version: 0.2.4
Summary: Shell-like interface with Zephyr Devicetree
Home-page: https://github.com/dottspina/dtsh
Author: Christophe Dufaza
Author-email: chris@openmarl.org
License: Apache License version 2.0
Keywords: devicetree,zephyr,dts,embedded
Classifier: Development Status :: 5 - Production/Stable
Classifier: Programming Language :: Python :: 3
Classifier: Intended Audience :: Developers
Classifier: Topic :: Software Development :: Embedded Systems
Classifier: License :: OSI Approved :: Apache Software License
Classifier: Programming Language :: Python :: 3 :: Only
Requires-Python: >=3.10
License-File: LICENSE
Requires-Dist: PyYAML>=6.0
Requires-Dist: rich
Requires-Dist: gnureadline; sys_platform == "darwin"
Provides-Extra: dev
Requires-Dist: pycodestyle; extra == "dev"
Requires-Dist: flake8; extra == "dev"
Requires-Dist: pylint; extra == "dev"
Requires-Dist: mypy; extra == "dev"
Requires-Dist: types-PyYAML; extra == "dev"
Requires-Dist: pytest; extra == "dev"
Provides-Extra: lsp
Requires-Dist: python-lsp-server[all]; extra == "lsp"
Requires-Dist: pylsp-mypy; extra == "lsp"
Requires-Dist: python-lsp-black; extra == "lsp"
Provides-Extra: dist
Requires-Dist: build; extra == "dist"
Requires-Dist: twine; extra == "dist"
